example_parlai_internal/README.md
example_parlai_internal/__init__.py
parlai/README.md
parlai/__init__.py
parlai/__main__.py
parlai/agents/README.md
parlai/agents/__init__.py
parlai/agents/alice/README.md
parlai/agents/alice/__init__.py
parlai/agents/alice/alice.py
parlai/agents/bart/README.md
parlai/agents/bart/__init__.py
parlai/agents/bart/bart.py
parlai/agents/bart/convert_fairseq_to_parlai.py
parlai/agents/bart/modules.py
parlai/agents/bert_classifier/README.md
parlai/agents/bert_classifier/__init__.py
parlai/agents/bert_classifier/bert_classifier.py
parlai/agents/bert_ranker/README.md
parlai/agents/bert_ranker/__init__.py
parlai/agents/bert_ranker/bert_dictionary.py
parlai/agents/bert_ranker/bert_ranker.py
parlai/agents/bert_ranker/bi_encoder_ranker.py
parlai/agents/bert_ranker/both_encoder_ranker.py
parlai/agents/bert_ranker/cross_encoder_ranker.py
parlai/agents/bert_ranker/helpers.py
parlai/agents/examples/README.md
parlai/agents/examples/__init__.py
parlai/agents/examples/seq2seq.py
parlai/agents/examples/tra.py
parlai/agents/examples/transformer_variant.py
parlai/agents/fid/README.md
parlai/agents/fid/__init__.py
parlai/agents/fid/fid.py
parlai/agents/fixed_response/README.md
parlai/agents/fixed_response/__init__.py
parlai/agents/fixed_response/fixed_response.py
parlai/agents/hred/README.md
parlai/agents/hred/__init__.py
parlai/agents/hred/hred.py
parlai/agents/hred/modules.py
parlai/agents/hugging_face/README.md
parlai/agents/hugging_face/__init__.py
parlai/agents/hugging_face/dialogpt.py
parlai/agents/hugging_face/dict.py
parlai/agents/hugging_face/gpt2.py
parlai/agents/hugging_face/hugging_face.py
parlai/agents/hugging_face/t5.py
parlai/agents/image_seq2seq/README.md
parlai/agents/image_seq2seq/__init__.py
parlai/agents/image_seq2seq/image_seq2seq.py
parlai/agents/image_seq2seq/modules.py
parlai/agents/ir_baseline/README.md
parlai/agents/ir_baseline/__init__.py
parlai/agents/ir_baseline/ir_baseline.py
parlai/agents/local_human/README.md
parlai-1.7.2.dist-info/LICENSE
parlai-1.7.2.dist-info/METADATA
parlai-1.7.2.dist-info/WHEEL
parlai-1.7.2.dist-info/entry_points.txt
parlai-1.7.2.dist-info/top_level.txt
parlai-1.7.2.dist-info/RECORD
