Metadata-Version: 2.1
Name: parlai
Version: 1.7.2
Summary: Unified platform for dialogue research.
Home-page: http://parl.ai/
Classifier: Programming Language :: Python :: 3
Classifier: License :: OSI Approved :: MIT License
Classifier: Topic :: Scientific/Engineering :: Artificial Intelligence
Classifier: Natural Language :: English
Requires-Python: >=3.8
License-File: LICENSE
Requires-Dist: coloredlogs
Requires-Dist: datasets (<2.2.2,>=1.4.1)
Requires-Dist: docutils (<0.16,>=0.14)
Requires-Dist: emoji
Requires-Dist: fairscale (~=0.4.1)
Requires-Dist: docformatter (~=1.4.0)
Requires-Dist: flake8-bugbear
Requires-Dist: flake8
Requires-Dist: fuzzywuzzy
Requires-Dist: google-cloud-storage
Requires-Dist: iopath (~=0.1.8)
Requires-Dist: gitdb2
Requires-Dist: GitPython
Requires-Dist: hydra-core (>=1.1.0)
Requires-Dist: ipython
Requires-Dist: torch
Requires-Dist: torchvision
Requires-Dist: joblib
Requires-Dist: nltk
Requires-Dist: omegaconf (>=2.1.1)
Requires-Dist: pandas
Requires-Dist: pytest-regressions
Requires-Dist: pytest
Requires-Dist: pexpect
Requires-Dist: Pillow
Requires-Dist: py-gfm
Requires-Dist: py-rouge
Requires-Dist: pyyaml
Requires-Dist: pyzmq
Requires-Dist: regex (>=2021.8.3)
Requires-Dist: myst-parser (<1)
Requires-Dist: attrs (~=20.2.0)
Requires-Dist: requests-mock
Requires-Dist: requests (<3,>=2.21.0)
Requires-Dist: scikit-learn
Requires-Dist: scipy
Requires-Dist: sh
Requires-Dist: sphinx-rtd-theme
Requires-Dist: sphinx-autodoc-typehints (~=1.10.3)
Requires-Dist: Sphinx (~=5.1.0)
Requires-Dist: subword-nmt
Requires-Dist: tensorboardX (<=2.5.0)
Requires-Dist: tokenizers (>=0.8.0)
Requires-Dist: tomli (>=2.0.0)
Requires-Dist: torchtext
Requires-Dist: tornado
Requires-Dist: tqdm (~=4.62.1)
Requires-Dist: typing-extensions
Requires-Dist: Unidecode
Requires-Dist: urllib3 (<1.27,>=1.26.5)
Requires-Dist: websocket-client
Requires-Dist: jsonlines
Requires-Dist: numpy (~=1.23.0)
Requires-Dist: markdown (<=3.3.2)
Requires-Dist: jinja2
Requires-Dist: ninja (~=1.10.2.3)
Requires-Dist: protobuf (<=3.20.3,>=3.8.0)
Requires-Dist: contractions (~=0.1.72)
Requires-Dist: fsspec (~=2022.2.0)
Requires-Dist: google-api-core (<=2.11.0)
